pybnf/__init__.py
pybnf/__main__.py
pybnf/algorithms.py
pybnf/cluster.py
pybnf/config.py
pybnf/constraint.py
pybnf/data.py
pybnf/objective.py
pybnf/parse.py
pybnf/printing.py
pybnf/pset.py
pybnf/pybnf.py
pybnf-1.2.2.dist-info/LICENSE
pybnf-1.2.2.dist-info/METADATA
pybnf-1.2.2.dist-info/WHEEL
pybnf-1.2.2.dist-info/entry_points.txt
pybnf-1.2.2.dist-info/top_level.txt
pybnf-1.2.2.dist-info/RECORD
