Metadata-Version: 2.1
Name: pybnf
Version: 1.2.2
Summary: An application for parallel fitting of BioNetGen and SBML models using metaheuristics
Home-page: UNKNOWN
Author: Eshan Mitra, Ryan Suderman, Alex Ionkov
License: UNKNOWN
Platform: UNKNOWN
Requires-Python: >=3.5
License-File: LICENSE
Requires-Dist: distributed (>=2021.6.2)
Requires-Dist: paramiko
Requires-Dist: msgpack (==0.6.2)
Requires-Dist: numpy
Requires-Dist: nose
Requires-Dist: pyparsing
Requires-Dist: libroadrunner (>=1.5.2)
Requires-Dist: dask (>=2021.5.0)
Requires-Dist: tornado (>=6.1)
Requires-Dist: scipy
